tecfilingfetcher
