Metadata-Version: 1.0
Name: tecfilingfetcher
Version: 0.0.3
Summary: A tool for processing raw filing files from the Texas Ethics Commission.
Home-page: https://github.com/rdmurphy/tecfilingfetcher
Author: Ryan Murphy
Author-email: rmurphy@texastribune.org
License: Copyright 2013 Ryan Murphy
